setup.py
dm/__init__.py
dm.zope.session.egg-info/PKG-INFO
dm.zope.session.egg-info/SOURCES.txt
dm.zope.session.egg-info/dependency_links.txt
dm.zope.session.egg-info/namespace_packages.txt
dm.zope.session.egg-info/not-zip-safe
dm.zope.session.egg-info/requires.txt
dm.zope.session.egg-info/top_level.txt
dm/zope/__init__.py
dm/zope/session/README.txt
dm/zope/session/VERSION.txt
dm/zope/session/__init__.py
dm/zope/session/configure.zcml
dm/zope/session/interfaces.py
dm/zope/session/tests.py