Metadata-Version: 1.1
Name: dm.zope.session
Version: 1.1
Summary: ZODB based heavy duty Zope session implementation.
Home-page: http://pypi.python.org/pypi/dm.zope.session
Author: Dieter Maurer
Author-email: dieter@handshake.de
License: ZPL
Keywords: session application development zope
Platform: UNKNOWN
Classifier: Development Status :: 5 - Production/Stable
Classifier: Intended Audience :: Developers
Classifier: License :: OSI Approved :: Zope Public License
Classifier: Framework :: Zope2
Classifier: Framework :: Zope
Classifier: Framework :: Zope :: 4
Classifier: Operating System :: OS Independent
Classifier: Programming Language :: Python
Classifier: Programming Language :: Python :: 2.7
Classifier: Programming Language :: Python :: 3
Classifier: Topic :: Utilities
